{
	"configurations" : 
	[
		{
			"directories" : 
			[
				{
					"build" : ".",
					"childIndexes" : 
					[
						1,
						2
					],
					"jsonFile" : "directory-.-Debug-d0094a50bb2071803777.json",
					"minimumCMakeVersion" : 
					{
						"string" : "3.10"
					},
					"projectIndex" : 0,
					"source" : ".",
					"targetIndexes" : 
					[
						0,
						1,
						3
					]
				},
				{
					"build" : "wrapper",
					"jsonFile" : "directory-wrapper-Debug-230ceb64303127ee682a.json",
					"minimumCMakeVersion" : 
					{
						"string" : "3.10"
					},
					"parentIndex" : 0,
					"projectIndex" : 0,
					"source" : "wrapper",
					"targetIndexes" : 
					[
						4
					]
				},
				{
					"build" : "application",
					"jsonFile" : "directory-application-Debug-42f45a6354a6cfac8278.json",
					"minimumCMakeVersion" : 
					{
						"string" : "3.10"
					},
					"parentIndex" : 0,
					"projectIndex" : 0,
					"source" : "application",
					"targetIndexes" : 
					[
						2
					]
				}
			],
			"name" : "Debug",
			"projects" : 
			[
				{
					"directoryIndexes" : 
					[
						0,
						1,
						2
					],
					"name" : "openGL_leture",
					"targetIndexes" : 
					[
						0,
						1,
						2,
						3,
						4
					]
				}
			],
			"targets" : 
			[
				{
					"directoryIndex" : 0,
					"id" : "ALL_BUILD::@6890427a1f51a3e7e1df",
					"jsonFile" : "target-ALL_BUILD-Debug-b10835fbd4f97dbad842.json",
					"name" : "ALL_BUILD",
					"projectIndex" : 0
				},
				{
					"directoryIndex" : 0,
					"id" : "ZERO_CHECK::@6890427a1f51a3e7e1df",
					"jsonFile" : "target-ZERO_CHECK-Debug-60156bb74854f172f480.json",
					"name" : "ZERO_CHECK",
					"projectIndex" : 0
				},
				{
					"directoryIndex" : 2,
					"id" : "app::@8badf0d542dc2e21c899",
					"jsonFile" : "target-app-Debug-82f552e88d3022c3a48b.json",
					"name" : "app",
					"projectIndex" : 0
				},
				{
					"directoryIndex" : 0,
					"id" : "openglStudy::@6890427a1f51a3e7e1df",
					"jsonFile" : "target-openglStudy-Debug-074bda8fdafcc2c036b9.json",
					"name" : "openglStudy",
					"projectIndex" : 0
				},
				{
					"directoryIndex" : 1,
					"id" : "wrapper::@cfb3dd9ac32c2b8e43a8",
					"jsonFile" : "target-wrapper-Debug-aebf73274e4e676b5e05.json",
					"name" : "wrapper",
					"projectIndex" : 0
				}
			]
		},
		{
			"directories" : 
			[
				{
					"build" : ".",
					"childIndexes" : 
					[
						1,
						2
					],
					"jsonFile" : "directory-.-Release-d0094a50bb2071803777.json",
					"minimumCMakeVersion" : 
					{
						"string" : "3.10"
					},
					"projectIndex" : 0,
					"source" : ".",
					"targetIndexes" : 
					[
						0,
						1,
						3
					]
				},
				{
					"build" : "wrapper",
					"jsonFile" : "directory-wrapper-Release-230ceb64303127ee682a.json",
					"minimumCMakeVersion" : 
					{
						"string" : "3.10"
					},
					"parentIndex" : 0,
					"projectIndex" : 0,
					"source" : "wrapper",
					"targetIndexes" : 
					[
						4
					]
				},
				{
					"build" : "application",
					"jsonFile" : "directory-application-Release-42f45a6354a6cfac8278.json",
					"minimumCMakeVersion" : 
					{
						"string" : "3.10"
					},
					"parentIndex" : 0,
					"projectIndex" : 0,
					"source" : "application",
					"targetIndexes" : 
					[
						2
					]
				}
			],
			"name" : "Release",
			"projects" : 
			[
				{
					"directoryIndexes" : 
					[
						0,
						1,
						2
					],
					"name" : "openGL_leture",
					"targetIndexes" : 
					[
						0,
						1,
						2,
						3,
						4
					]
				}
			],
			"targets" : 
			[
				{
					"directoryIndex" : 0,
					"id" : "ALL_BUILD::@6890427a1f51a3e7e1df",
					"jsonFile" : "target-ALL_BUILD-Release-b10835fbd4f97dbad842.json",
					"name" : "ALL_BUILD",
					"projectIndex" : 0
				},
				{
					"directoryIndex" : 0,
					"id" : "ZERO_CHECK::@6890427a1f51a3e7e1df",
					"jsonFile" : "target-ZERO_CHECK-Release-60156bb74854f172f480.json",
					"name" : "ZERO_CHECK",
					"projectIndex" : 0
				},
				{
					"directoryIndex" : 2,
					"id" : "app::@8badf0d542dc2e21c899",
					"jsonFile" : "target-app-Release-c2428bdb2af79d42b69b.json",
					"name" : "app",
					"projectIndex" : 0
				},
				{
					"directoryIndex" : 0,
					"id" : "openglStudy::@6890427a1f51a3e7e1df",
					"jsonFile" : "target-openglStudy-Release-bbf7d3b99d16cf1376cf.json",
					"name" : "openglStudy",
					"projectIndex" : 0
				},
				{
					"directoryIndex" : 1,
					"id" : "wrapper::@cfb3dd9ac32c2b8e43a8",
					"jsonFile" : "target-wrapper-Release-e7ca32a39e2c908cc44a.json",
					"name" : "wrapper",
					"projectIndex" : 0
				}
			]
		},
		{
			"directories" : 
			[
				{
					"build" : ".",
					"childIndexes" : 
					[
						1,
						2
					],
					"jsonFile" : "directory-.-MinSizeRel-d0094a50bb2071803777.json",
					"minimumCMakeVersion" : 
					{
						"string" : "3.10"
					},
					"projectIndex" : 0,
					"source" : ".",
					"targetIndexes" : 
					[
						0,
						1,
						3
					]
				},
				{
					"build" : "wrapper",
					"jsonFile" : "directory-wrapper-MinSizeRel-230ceb64303127ee682a.json",
					"minimumCMakeVersion" : 
					{
						"string" : "3.10"
					},
					"parentIndex" : 0,
					"projectIndex" : 0,
					"source" : "wrapper",
					"targetIndexes" : 
					[
						4
					]
				},
				{
					"build" : "application",
					"jsonFile" : "directory-application-MinSizeRel-42f45a6354a6cfac8278.json",
					"minimumCMakeVersion" : 
					{
						"string" : "3.10"
					},
					"parentIndex" : 0,
					"projectIndex" : 0,
					"source" : "application",
					"targetIndexes" : 
					[
						2
					]
				}
			],
			"name" : "MinSizeRel",
			"projects" : 
			[
				{
					"directoryIndexes" : 
					[
						0,
						1,
						2
					],
					"name" : "openGL_leture",
					"targetIndexes" : 
					[
						0,
						1,
						2,
						3,
						4
					]
				}
			],
			"targets" : 
			[
				{
					"directoryIndex" : 0,
					"id" : "ALL_BUILD::@6890427a1f51a3e7e1df",
					"jsonFile" : "target-ALL_BUILD-MinSizeRel-b10835fbd4f97dbad842.json",
					"name" : "ALL_BUILD",
					"projectIndex" : 0
				},
				{
					"directoryIndex" : 0,
					"id" : "ZERO_CHECK::@6890427a1f51a3e7e1df",
					"jsonFile" : "target-ZERO_CHECK-MinSizeRel-60156bb74854f172f480.json",
					"name" : "ZERO_CHECK",
					"projectIndex" : 0
				},
				{
					"directoryIndex" : 2,
					"id" : "app::@8badf0d542dc2e21c899",
					"jsonFile" : "target-app-MinSizeRel-90adefdc221c85056afc.json",
					"name" : "app",
					"projectIndex" : 0
				},
				{
					"directoryIndex" : 0,
					"id" : "openglStudy::@6890427a1f51a3e7e1df",
					"jsonFile" : "target-openglStudy-MinSizeRel-fe3e06a18469e434dba3.json",
					"name" : "openglStudy",
					"projectIndex" : 0
				},
				{
					"directoryIndex" : 1,
					"id" : "wrapper::@cfb3dd9ac32c2b8e43a8",
					"jsonFile" : "target-wrapper-MinSizeRel-42293cb88d31d862922a.json",
					"name" : "wrapper",
					"projectIndex" : 0
				}
			]
		},
		{
			"directories" : 
			[
				{
					"build" : ".",
					"childIndexes" : 
					[
						1,
						2
					],
					"jsonFile" : "directory-.-RelWithDebInfo-d0094a50bb2071803777.json",
					"minimumCMakeVersion" : 
					{
						"string" : "3.10"
					},
					"projectIndex" : 0,
					"source" : ".",
					"targetIndexes" : 
					[
						0,
						1,
						3
					]
				},
				{
					"build" : "wrapper",
					"jsonFile" : "directory-wrapper-RelWithDebInfo-230ceb64303127ee682a.json",
					"minimumCMakeVersion" : 
					{
						"string" : "3.10"
					},
					"parentIndex" : 0,
					"projectIndex" : 0,
					"source" : "wrapper",
					"targetIndexes" : 
					[
						4
					]
				},
				{
					"build" : "application",
					"jsonFile" : "directory-application-RelWithDebInfo-42f45a6354a6cfac8278.json",
					"minimumCMakeVersion" : 
					{
						"string" : "3.10"
					},
					"parentIndex" : 0,
					"projectIndex" : 0,
					"source" : "application",
					"targetIndexes" : 
					[
						2
					]
				}
			],
			"name" : "RelWithDebInfo",
			"projects" : 
			[
				{
					"directoryIndexes" : 
					[
						0,
						1,
						2
					],
					"name" : "openGL_leture",
					"targetIndexes" : 
					[
						0,
						1,
						2,
						3,
						4
					]
				}
			],
			"targets" : 
			[
				{
					"directoryIndex" : 0,
					"id" : "ALL_BUILD::@6890427a1f51a3e7e1df",
					"jsonFile" : "target-ALL_BUILD-RelWithDebInfo-b10835fbd4f97dbad842.json",
					"name" : "ALL_BUILD",
					"projectIndex" : 0
				},
				{
					"directoryIndex" : 0,
					"id" : "ZERO_CHECK::@6890427a1f51a3e7e1df",
					"jsonFile" : "target-ZERO_CHECK-RelWithDebInfo-60156bb74854f172f480.json",
					"name" : "ZERO_CHECK",
					"projectIndex" : 0
				},
				{
					"directoryIndex" : 2,
					"id" : "app::@8badf0d542dc2e21c899",
					"jsonFile" : "target-app-RelWithDebInfo-56680651d35c2dcb3367.json",
					"name" : "app",
					"projectIndex" : 0
				},
				{
					"directoryIndex" : 0,
					"id" : "openglStudy::@6890427a1f51a3e7e1df",
					"jsonFile" : "target-openglStudy-RelWithDebInfo-5d1ef4cd211311dabe0e.json",
					"name" : "openglStudy",
					"projectIndex" : 0
				},
				{
					"directoryIndex" : 1,
					"id" : "wrapper::@cfb3dd9ac32c2b8e43a8",
					"jsonFile" : "target-wrapper-RelWithDebInfo-b93d0479744d6a5908b1.json",
					"name" : "wrapper",
					"projectIndex" : 0
				}
			]
		}
	],
	"kind" : "codemodel",
	"paths" : 
	{
		"build" : "E:/Dev/C++/OpenGL/04_OpenGL_Application/build",
		"source" : "E:/Dev/C++/OpenGL/04_OpenGL_Application"
	},
	"version" : 
	{
		"major" : 2,
		"minor" : 7
	}
}
